corehttp/__init__.py
corehttp/_match_conditions.py
corehttp/_version.py
corehttp/credentials.py
corehttp/exceptions.py
corehttp/paging.py
corehttp/py.typed
corehttp/serialization.py
corehttp/rest/__init__.py
corehttp/rest/_aiohttp.py
corehttp/rest/_helpers.py
corehttp/rest/_http_response_impl.py
corehttp/rest/_http_response_impl_async.py
corehttp/rest/_httpx.py
corehttp/rest/_requests_basic.py
corehttp/rest/_rest_py3.py
corehttp/runtime/__init__.py
corehttp/runtime/_base.py
corehttp/runtime/_pipeline_client.py
corehttp/runtime/_pipeline_client_async.py
corehttp/runtime/pipeline/__init__.py
corehttp/runtime/pipeline/_base.py
corehttp/runtime/pipeline/_base_async.py
corehttp/runtime/pipeline/_tools.py
corehttp/runtime/pipeline/_tools_async.py
corehttp/runtime/policies/__init__.py
corehttp/runtime/policies/_authentication.py
corehttp/runtime/policies/_authentication_async.py
corehttp/runtime/policies/_base.py
corehttp/runtime/policies/_base_async.py
corehttp/runtime/policies/_retry.py
corehttp/runtime/policies/_retry_async.py
corehttp/runtime/policies/_universal.py
corehttp/runtime/policies/_utils.py
corehttp/transport/__init__.py
corehttp/transport/_base.py
corehttp/transport/_base_async.py
corehttp/transport/aiohttp/__init__.py
corehttp/transport/aiohttp/_aiohttp.py
corehttp/transport/httpx/__init__.py
corehttp/transport/httpx/_httpx.py
corehttp/transport/requests/__init__.py
corehttp/transport/requests/_bigger_block_size_http_adapters.py
corehttp/transport/requests/_requests_basic.py
corehttp/utils/__init__.py
corehttp/utils/_enum_meta.py
corehttp/utils/_utils.py
corehttp-1.0.0b6.dist-info/LICENSE
corehttp-1.0.0b6.dist-info/METADATA
corehttp-1.0.0b6.dist-info/WHEEL
corehttp-1.0.0b6.dist-info/top_level.txt
corehttp-1.0.0b6.dist-info/RECORD
