Metadata-Version: 2.1
Name: corehttp
Version: 1.0.0b6
Summary: CoreHTTP Library for Python
Home-page: https://github.com/Azure/azure-sdk-for-python/tree/main/sdk/core/corehttp
Author: Microsoft Corporation
Author-email: azpysdkhelp@microsoft.com
License: MIT License
Keywords: typespec,core
Classifier: Development Status :: 4 - Beta
Classifier: Programming Language :: Python
Classifier: Programming Language :: Python :: 3 :: Only
Classifier: Programming Language :: Python :: 3
Classifier: Programming Language :: Python :: 3.8
Classifier: Programming Language :: Python :: 3.9
Classifier: Programming Language :: Python :: 3.10
Classifier: Programming Language :: Python :: 3.11
Classifier: Programming Language :: Python :: 3.12
Classifier: License :: OSI Approved :: MIT License
Requires-Python: >=3.8
License-File: LICENSE
Requires-Dist: typing-extensions>=4.6.0
Provides-Extra: aiohttp
Requires-Dist: aiohttp>=3.0; extra == "aiohttp"
Provides-Extra: httpx
Requires-Dist: httpx>=0.25.0; extra == "httpx"
Provides-Extra: requests
Requires-Dist: requests>=2.18.4; extra == "requests"
